[
  {
    "title": "My cat",
    "text": "is cuter",
    "id": "1e90"
  },
  {
    "title": "My dog ",
    "text": "to clean him today\n",
    "id": "2d90"
  },
  {
    "title": "hello",
    "text": "world",
    "id": "badb"
  },
  {
    "title": "hello",
    "text": "world",
    "id": "e61d"
  },
  {
    "title": "hello",
    "text": "world",
    "id": "b27f"
  },
  {
    "title": "hello",
    "text": "world",
    "id": "96ad"
  },
  {
    "title": "hello",
    "text": "world",
    "id": "c7dc"
  }
]